adaptivecard/__init__.py
adaptivecard/_base_types.py
adaptivecard/_mixin.py
adaptivecard/_type_checker.py
adaptivecard/_typing.py
adaptivecard/_utils.py
adaptivecard/actions.py
adaptivecard/card_elements.py
adaptivecard/containers.py
adaptivecard/exceptions.py
adaptivecard/inputs.py
adaptivecard/schemas/__init__.py
adaptivecard/schemas/schema.json
tests/__init__.py
tests/integration/__init__.py
tests/integration/test_integration.py
tests/unit/__init__.py
tests/unit/test_actions.py
tests/unit/test_containers.py
tests/unit/test_init.py
tests/unit/test_inputs.py
adaptivecard-0.3.1.dist-info/LICENSE.txt
adaptivecard-0.3.1.dist-info/METADATA
adaptivecard-0.3.1.dist-info/WHEEL
adaptivecard-0.3.1.dist-info/top_level.txt
adaptivecard-0.3.1.dist-info/RECORD
