Metadata-Version: 2.1
Name: adaptivecard
Version: 0.3.1
Summary: Microsoft Adaptive Cards
Author: cabutchei (Luan Paz)
Author-email: <luropa_paz@hotmail.com>
Keywords: python,adaptive,cards,microsoft
Classifier: Development Status :: 3 - Alpha
Classifier: Intended Audience :: Developers
Classifier: License :: OSI Approved :: MIT License
Classifier: Programming Language :: Python :: 3
Classifier: Operating System :: Unix
Classifier: Operating System :: MacOS :: MacOS X
Classifier: Operating System :: Microsoft :: Windows
License-File: LICENSE.txt
Requires-Dist: jsonschema ~=4.23.0
